python_ecies/__init__.py
python_ecies/common.py
python_ecies/ecies.py
python_ecies/factory.py
python_ecies/format.py
python_ecies/key_derivation.py
python_ecies/py.typed
python_ecies/symmetric.py
python_ecies/yubihsm_helper.py
python_ecies-0.1.1.dist-info/LICENSE.txt
python_ecies-0.1.1.dist-info/METADATA
python_ecies-0.1.1.dist-info/WHEEL
python_ecies-0.1.1.dist-info/top_level.txt
python_ecies-0.1.1.dist-info/RECORD
